{"PATH":"9\/1200\/details.html","NODES":{"BEFORE_CHANGE":[{"LABEL":"function.rearrange()","DATA_TYPE":"function.rearrange()"},{"LABEL":"Str","DATA_TYPE":"String"},{"LABEL":"Assign:=","DATA_TYPE":null}],"AFTER_CHANGE":[{"LABEL":"function.map()","DATA_TYPE":"function.map()"},{"LABEL":"()","DATA_TYPE":"()"},{"LABEL":"Assign:=","DATA_TYPE":null},{"LABEL":"()","DATA_TYPE":"()"},{"LABEL":"Name","DATA_TYPE":"nothing"},{"LABEL":"Name","DATA_TYPE":"nothing"},{"LABEL":"Name","DATA_TYPE":"nothing"},{"LABEL":"Name","DATA_TYPE":"nothing"}]},"NUMBER_OF_REPEATED_NODES":9,"Fragments":[{"M FILE_NAME":"dalle_pytorch\/attention.py","PROJECT_NAME":"lucidrains\/dalle-pytorch","COMMITTER_EMAIL":"lucidrains@gmail.com","START_LINE_AFTER_CODE":129,"NODE_INFO":[{"END_CHARACTER":6789,"START_LINE_NUMBER":190,"AST_CLASS":"Name","LENGTH":11,"START_CHARACTER":6778,"VERSION":0,"LABEL":"W","DATA_TYPE":"Any","END_LINE_NUMBER":190},{"END_CHARACTER":5900,"START_LINE_NUMBER":172,"AST_CLASS":"Name","LENGTH":5,"START_CHARACTER":5895,"VERSION":1,"LABEL":"W","DATA_TYPE":"nothing","END_LINE_NUMBER":172},{"END_CHARACTER":6632,"START_LINE_NUMBER":185,"AST_CLASS":"Name","LENGTH":13,"START_CHARACTER":6619,"VERSION":0,"LABEL":"W","DATA_TYPE":"Any","END_LINE_NUMBER":185},{"END_CHARACTER":0,"START_LINE_NUMBER":0,"AST_CLASS":"Name","LENGTH":0,"START_CHARACTER":0,"VERSION":1,"LABEL":"W","DATA_TYPE":"nothing","END_LINE_NUMBER":0},{"END_CHARACTER":6822,"START_LINE_NUMBER":190,"AST_CLASS":"Assign","LENGTH":4,"START_CHARACTER":6789,"VERSION":0,"LABEL":"½","DATA_TYPE":null,"END_LINE_NUMBER":190},{"END_CHARACTER":6732,"START_LINE_NUMBER":189,"AST_CLASS":"Name","LENGTH":13,"START_CHARACTER":6719,"VERSION":0,"LABEL":"W","DATA_TYPE":"Any","END_LINE_NUMBER":189},{"END_CHARACTER":5592,"START_LINE_NUMBER":167,"AST_CLASS":"Name","LENGTH":7,"START_CHARACTER":5585,"VERSION":0,"LABEL":"W","DATA_TYPE":"Any","END_LINE_NUMBER":167},{"END_CHARACTER":6768,"START_LINE_NUMBER":189,"AST_CLASS":"Str","LENGTH":14,"START_CHARACTER":6754,"VERSION":0,"LABEL":"B","DATA_TYPE":"String","END_LINE_NUMBER":189},{"END_CHARACTER":6752,"START_LINE_NUMBER":189,"AST_CLASS":"Name","LENGTH":7,"START_CHARACTER":6745,"VERSION":0,"LABEL":"W","DATA_TYPE":"Any","END_LINE_NUMBER":189},{"END_CHARACTER":6896,"START_LINE_NUMBER":191,"AST_CLASS":"Name","LENGTH":11,"START_CHARACTER":6885,"VERSION":1,"LABEL":"W","DATA_TYPE":"Any","END_LINE_NUMBER":191},{"END_CHARACTER":6587,"START_LINE_NUMBER":185,"AST_CLASS":"Name","LENGTH":14,"START_CHARACTER":6573,"VERSION":1,"LABEL":"W","DATA_TYPE":"Tuple[Any, int, Any, int]","END_LINE_NUMBER":185},{"END_CHARACTER":5669,"START_LINE_NUMBER":168,"AST_CLASS":"BinOp","LENGTH":3,"START_CHARACTER":5665,"VERSION":1,"LABEL":"á","DATA_TYPE":null,"END_LINE_NUMBER":168},{"END_CHARACTER":5669,"START_LINE_NUMBER":168,"AST_CLASS":"Num","LENGTH":1,"START_CHARACTER":5668,"VERSION":1,"LABEL":"L","DATA_TYPE":"number","END_LINE_NUMBER":168},{"END_CHARACTER":6822,"START_LINE_NUMBER":190,"AST_CLASS":"Compare","LENGTH":29,"START_CHARACTER":6793,"VERSION":0,"LABEL":"ò","DATA_TYPE":null,"END_LINE_NUMBER":190},{"END_CHARACTER":5665,"START_LINE_NUMBER":168,"AST_CLASS":"Name","LENGTH":12,"START_CHARACTER":5653,"VERSION":1,"LABEL":"W","DATA_TYPE":"Any","END_LINE_NUMBER":168},{"END_CHARACTER":5893,"START_LINE_NUMBER":172,"AST_CLASS":"Tuple","LENGTH":7,"START_CHARACTER":5893,"VERSION":1,"LABEL":"()","DATA_TYPE":"()","END_LINE_NUMBER":172},{"END_CHARACTER":5597,"START_LINE_NUMBER":167,"AST_CLASS":"Name","LENGTH":12,"START_CHARACTER":5585,"VERSION":1,"LABEL":"W","DATA_TYPE":"Any","END_LINE_NUMBER":167},{"END_CHARACTER":6896,"START_LINE_NUMBER":191,"AST_CLASS":"Compare","LENGTH":28,"START_CHARACTER":6868,"VERSION":1,"LABEL":"ò","DATA_TYPE":null,"END_LINE_NUMBER":191},{"END_CHARACTER":6454,"START_LINE_NUMBER":183,"AST_CLASS":"BinOp","LENGTH":3,"START_CHARACTER":6450,"VERSION":0,"LABEL":"á","DATA_TYPE":null,"END_LINE_NUMBER":183},{"END_CHARACTER":5690,"START_LINE_NUMBER":168,"AST_CLASS":"BinOp","LENGTH":3,"START_CHARACTER":5686,"VERSION":1,"LABEL":"á","DATA_TYPE":null,"END_LINE_NUMBER":168},{"END_CHARACTER":6864,"START_LINE_NUMBER":191,"AST_CLASS":"Name","LENGTH":12,"START_CHARACTER":6852,"VERSION":1,"LABEL":"W","DATA_TYPE":"Any","END_LINE_NUMBER":191},{"END_CHARACTER":6769,"START_LINE_NUMBER":189,"AST_CLASS":"Assign","LENGTH":3,"START_CHARACTER":6732,"VERSION":0,"LABEL":"½","DATA_TYPE":null,"END_LINE_NUMBER":189},{"END_CHARACTER":6262,"START_LINE_NUMBER":181,"AST_CLASS":"Name","LENGTH":7,"START_CHARACTER":6255,"VERSION":0,"LABEL":"W","DATA_TYPE":"Any","END_LINE_NUMBER":181},{"END_CHARACTER":5978,"START_LINE_NUMBER":172,"AST_CLASS":"Tuple","LENGTH":7,"START_CHARACTER":5970,"VERSION":1,"LABEL":"()","DATA_TYPE":"()","END_LINE_NUMBER":172},{"END_CHARACTER":0,"START_LINE_NUMBER":0,"AST_CLASS":"Name","LENGTH":0,"START_CHARACTER":0,"VERSION":1,"LABEL":"W","DATA_TYPE":"nothing","END_LINE_NUMBER":0},{"END_CHARACTER":6822,"START_LINE_NUMBER":190,"AST_CLASS":"Name","LENGTH":13,"START_CHARACTER":6809,"VERSION":0,"LABEL":"W","DATA_TYPE":"Any","END_LINE_NUMBER":190},{"END_CHARACTER":5693,"START_LINE_NUMBER":168,"AST_CLASS":"Num","LENGTH":1,"START_CHARACTER":5692,"VERSION":1,"LABEL":"L","DATA_TYPE":"number","END_LINE_NUMBER":168},{"END_CHARACTER":6896,"START_LINE_NUMBER":191,"AST_CLASS":"Assign","LENGTH":4,"START_CHARACTER":6864,"VERSION":1,"LABEL":"½","DATA_TYPE":null,"END_LINE_NUMBER":191},{"END_CHARACTER":0,"START_LINE_NUMBER":0,"AST_CLASS":"Name","LENGTH":0,"START_CHARACTER":0,"VERSION":1,"LABEL":"W","DATA_TYPE":"Tuple[Any, int, Any, int]","END_LINE_NUMBER":0},{"END_CHARACTER":5977,"START_LINE_NUMBER":172,"AST_CLASS":"Name","LENGTH":5,"START_CHARACTER":5972,"VERSION":1,"LABEL":"W","DATA_TYPE":"nothing","END_LINE_NUMBER":172},{"END_CHARACTER":6448,"START_LINE_NUMBER":183,"AST_CLASS":"Name","LENGTH":7,"START_CHARACTER":6441,"VERSION":0,"LABEL":"W","DATA_TYPE":"Any","END_LINE_NUMBER":183},{"END_CHARACTER":5672,"START_LINE_NUMBER":168,"AST_CLASS":"Num","LENGTH":1,"START_CHARACTER":5671,"VERSION":1,"LABEL":"L","DATA_TYPE":"number","END_LINE_NUMBER":168},{"END_CHARACTER":5686,"START_LINE_NUMBER":168,"AST_CLASS":"Name","LENGTH":12,"START_CHARACTER":5674,"VERSION":1,"LABEL":"W","DATA_TYPE":"Any","END_LINE_NUMBER":168},{"END_CHARACTER":5649,"START_LINE_NUMBER":168,"AST_CLASS":"Name","LENGTH":14,"START_CHARACTER":5635,"VERSION":1,"LABEL":"W","DATA_TYPE":"Tuple[Any, int, Any, int]","END_LINE_NUMBER":168},{"END_CHARACTER":5690,"START_LINE_NUMBER":168,"AST_CLASS":"Num","LENGTH":1,"START_CHARACTER":5689,"VERSION":1,"LABEL":"L","DATA_TYPE":"number","END_LINE_NUMBER":168},{"END_CHARACTER":6454,"START_LINE_NUMBER":183,"AST_CLASS":"Num","LENGTH":1,"START_CHARACTER":6453,"VERSION":0,"LABEL":"L","DATA_TYPE":"number","END_LINE_NUMBER":183},{"END_CHARACTER":5979,"START_LINE_NUMBER":172,"AST_CLASS":"Assign","LENGTH":10,"START_CHARACTER":5893,"VERSION":1,"LABEL":"½","DATA_TYPE":null,"END_LINE_NUMBER":172},{"END_CHARACTER":5893,"START_LINE_NUMBER":172,"AST_CLASS":"Name","LENGTH":5,"START_CHARACTER":5888,"VERSION":1,"LABEL":"W","DATA_TYPE":"nothing","END_LINE_NUMBER":172},{"END_CHARACTER":6806,"START_LINE_NUMBER":190,"AST_CLASS":"Name","LENGTH":13,"START_CHARACTER":6793,"VERSION":0,"LABEL":"W","DATA_TYPE":"Any","END_LINE_NUMBER":190},{"END_CHARACTER":4322,"START_LINE_NUMBER":129,"AST_CLASS":"Name","LENGTH":11,"START_CHARACTER":4311,"VERSION":1,"LABEL":"W","DATA_TYPE":"Any","END_LINE_NUMBER":129},{"END_CHARACTER":6769,"START_LINE_NUMBER":189,"AST_CLASS":"Call","LENGTH":10,"START_CHARACTER":6735,"VERSION":0,"LABEL":"function.rearrange()","DATA_TYPE":"function.rearrange()","END_LINE_NUMBER":189},{"END_CHARACTER":5970,"START_LINE_NUMBER":172,"AST_CLASS":"Name","LENGTH":5,"START_CHARACTER":5965,"VERSION":1,"LABEL":"W","DATA_TYPE":"nothing","END_LINE_NUMBER":172},{"END_CHARACTER":5649,"START_LINE_NUMBER":168,"AST_CLASS":"Name","LENGTH":14,"START_CHARACTER":5635,"VERSION":1,"LABEL":"W","DATA_TYPE":"Tuple[Any, int, Any, int]","END_LINE_NUMBER":168},{"END_CHARACTER":6450,"START_LINE_NUMBER":183,"AST_CLASS":"Tuple","LENGTH":0,"START_CHARACTER":6448,"VERSION":0,"LABEL":"()","DATA_TYPE":"()","END_LINE_NUMBER":183},{"END_CHARACTER":5694,"START_LINE_NUMBER":168,"AST_CLASS":"Tuple","LENGTH":24,"START_CHARACTER":5669,"VERSION":1,"LABEL":"()","DATA_TYPE":"()","END_LINE_NUMBER":168},{"END_CHARACTER":5979,"START_LINE_NUMBER":172,"AST_CLASS":"Call","LENGTH":4,"START_CHARACTER":5903,"VERSION":1,"LABEL":"function.map()","DATA_TYPE":"function.map()","END_LINE_NUMBER":172},{"END_CHARACTER":6765,"START_LINE_NUMBER":187,"AST_CLASS":"Name","LENGTH":13,"START_CHARACTER":6752,"VERSION":1,"LABEL":"W","DATA_TYPE":"Any","END_LINE_NUMBER":187},{"END_CHARACTER":6881,"START_LINE_NUMBER":191,"AST_CLASS":"Name","LENGTH":13,"START_CHARACTER":6868,"VERSION":1,"LABEL":"W","DATA_TYPE":"Any","END_LINE_NUMBER":191}],"COMMITTER_NAME":"Phil Wang","LINK":"https:\/\/github.com\/lucidrains\/dalle-pytorch\/commit\/3064403976ee2fadacef934e789cdd9f4de118ec#diff-58807b9968341c05944b3adf3de1bfcd9d33660121a78f3ef013fd0e9bf16fdfL129","COMMIT_NAME":"3064403976ee2fadacef934e789cdd9f4de118ec","AUTHOR_EMAIL":"lucidrains@gmail.com","N FILE_NAME":"dalle_pytorch\/attention.py","M CLASS_NAME":"SparseConvCausalAttention","N METHOD_NAME":"forward(4)","START_LINE_BEFORE_CODE":167,"M METHOD_NAME":"forward(4)","PARENT_CLASS":"nn.Module","END_LINE_BEFORE_CODE":190,"END_CHARACTER_BEFORE_CODE":6822,"TIME":"2022-03-23","AUTHOR_NAME":"Phil Wang","START_CHARACTER_BEFORE_CODE":5585,"END_LINE_AFTER_CODE":191,"N CLASS_NAME":"SparseConvCausalAttention","FRAGMENT_ID":4347339,"END_CHARACTER_AFTER_CODE":6896,"START_CHARACTER_AFTER_CODE":4311},{"M FILE_NAME":"adjacent_attention_network\/adjacent_attention_network.py","PROJECT_NAME":"lucidrains\/adjacent-attention-network","COMMITTER_EMAIL":"lucidrains@gmail.com","START_LINE_AFTER_CODE":78,"NODE_INFO":[{"END_CHARACTER":2294,"START_LINE_NUMBER":86,"AST_CLASS":"Name","LENGTH":1,"START_CHARACTER":2293,"VERSION":1,"LABEL":"W","DATA_TYPE":"nothing","END_LINE_NUMBER":86},{"END_CHARACTER":2359,"START_LINE_NUMBER":87,"AST_CLASS":"Call","LENGTH":21,"START_CHARACTER":2322,"VERSION":1,"LABEL":"function.batched_index_select()","DATA_TYPE":"function.batched_index_select()","END_LINE_NUMBER":87},{"END_CHARACTER":2450,"START_LINE_NUMBER":88,"AST_CLASS":"Name","LENGTH":1,"START_CHARACTER":2449,"VERSION":0,"LABEL":"W","DATA_TYPE":"Any","END_LINE_NUMBER":88},{"END_CHARACTER":2042,"START_LINE_NUMBER":82,"AST_CLASS":"Tuple","LENGTH":6,"START_CHARACTER":2042,"VERSION":1,"LABEL":"()","DATA_TYPE":"()","END_LINE_NUMBER":82},{"END_CHARACTER":2454,"START_LINE_NUMBER":88,"AST_CLASS":"Call","LENGTH":4,"START_CHARACTER":2375,"VERSION":1,"LABEL":"function.map()","DATA_TYPE":"function.map()","END_LINE_NUMBER":88},{"END_CHARACTER":2336,"START_LINE_NUMBER":87,"AST_CLASS":"Name","LENGTH":1,"START_CHARACTER":2335,"VERSION":0,"LABEL":"W","DATA_TYPE":"Any","END_LINE_NUMBER":87},{"END_CHARACTER":0,"START_LINE_NUMBER":0,"AST_CLASS":"Name","LENGTH":0,"START_CHARACTER":0,"VERSION":1,"LABEL":"W","DATA_TYPE":"Any","END_LINE_NUMBER":0},{"END_CHARACTER":1944,"START_LINE_NUMBER":78,"AST_CLASS":"Assign","LENGTH":3,"START_CHARACTER":1888,"VERSION":1,"LABEL":"½","DATA_TYPE":null,"END_LINE_NUMBER":78},{"END_CHARACTER":2322,"START_LINE_NUMBER":87,"AST_CLASS":"Name","LENGTH":1,"START_CHARACTER":2321,"VERSION":0,"LABEL":"W","DATA_TYPE":"Any","END_LINE_NUMBER":87},{"END_CHARACTER":0,"START_LINE_NUMBER":0,"AST_CLASS":"Name","LENGTH":0,"START_CHARACTER":0,"VERSION":1,"LABEL":"W","DATA_TYPE":"nothing","END_LINE_NUMBER":0},{"END_CHARACTER":2449,"START_LINE_NUMBER":88,"AST_CLASS":"Name","LENGTH":1,"START_CHARACTER":2448,"VERSION":1,"LABEL":"W","DATA_TYPE":"nothing","END_LINE_NUMBER":88},{"END_CHARACTER":0,"START_LINE_NUMBER":0,"AST_CLASS":"Name","LENGTH":0,"START_CHARACTER":0,"VERSION":1,"LABEL":"W","DATA_TYPE":"Any","END_LINE_NUMBER":0},{"END_CHARACTER":2358,"START_LINE_NUMBER":87,"AST_CLASS":"Name","LENGTH":12,"START_CHARACTER":2346,"VERSION":1,"LABEL":"W","DATA_TYPE":"Any","END_LINE_NUMBER":87},{"END_CHARACTER":2032,"START_LINE_NUMBER":81,"AST_CLASS":"Call","LENGTH":21,"START_CHARACTER":1999,"VERSION":1,"LABEL":"chunk()","DATA_TYPE":"chunk()","END_LINE_NUMBER":81},{"END_CHARACTER":2119,"START_LINE_NUMBER":82,"AST_CLASS":"Tuple","LENGTH":6,"START_CHARACTER":2112,"VERSION":1,"LABEL":"()","DATA_TYPE":"()","END_LINE_NUMBER":82},{"END_CHARACTER":1939,"START_LINE_NUMBER":79,"AST_CLASS":"Name","LENGTH":12,"START_CHARACTER":1927,"VERSION":0,"LABEL":"W","DATA_TYPE":"Any","END_LINE_NUMBER":79},{"END_CHARACTER":2257,"START_LINE_NUMBER":85,"AST_CLASS":"Name","LENGTH":1,"START_CHARACTER":2256,"VERSION":1,"LABEL":"W","DATA_TYPE":"nothing","END_LINE_NUMBER":85},{"END_CHARACTER":2273,"START_LINE_NUMBER":86,"AST_CLASS":"Name","LENGTH":1,"START_CHARACTER":2272,"VERSION":0,"LABEL":"W","DATA_TYPE":"Any","END_LINE_NUMBER":86},{"END_CHARACTER":2308,"START_LINE_NUMBER":86,"AST_CLASS":"Name","LENGTH":12,"START_CHARACTER":2296,"VERSION":1,"LABEL":"W","DATA_TYPE":"Any","END_LINE_NUMBER":86},{"END_CHARACTER":2455,"START_LINE_NUMBER":88,"AST_CLASS":"Call","LENGTH":4,"START_CHARACTER":2384,"VERSION":0,"LABEL":"function.map()","DATA_TYPE":"function.map()","END_LINE_NUMBER":88},{"END_CHARACTER":2144,"START_LINE_NUMBER":82,"AST_CLASS":"Name","LENGTH":12,"START_CHARACTER":2132,"VERSION":0,"LABEL":"W","DATA_TYPE":"Any","END_LINE_NUMBER":82},{"END_CHARACTER":2120,"START_LINE_NUMBER":82,"AST_CLASS":"Call","LENGTH":4,"START_CHARACTER":2051,"VERSION":1,"LABEL":"function.map()","DATA_TYPE":"function.map()","END_LINE_NUMBER":82},{"END_CHARACTER":2266,"START_LINE_NUMBER":86,"AST_CLASS":"Tuple","LENGTH":38,"START_CHARACTER":2274,"VERSION":0,"LABEL":"()","DATA_TYPE":"()","END_LINE_NUMBER":86},{"END_CHARACTER":0,"START_LINE_NUMBER":0,"AST_CLASS":"Name","LENGTH":0,"START_CHARACTER":0,"VERSION":1,"LABEL":"W","DATA_TYPE":"Any","END_LINE_NUMBER":0},{"END_CHARACTER":2309,"START_LINE_NUMBER":86,"AST_CLASS":"Call","LENGTH":21,"START_CHARACTER":2272,"VERSION":1,"LABEL":"function.batched_index_select()","DATA_TYPE":"function.batched_index_select()","END_LINE_NUMBER":86},{"END_CHARACTER":0,"START_LINE_NUMBER":0,"AST_CLASS":"Name","LENGTH":0,"START_CHARACTER":0,"VERSION":1,"LABEL":"W","DATA_TYPE":"nothing","END_LINE_NUMBER":0},{"END_CHARACTER":2344,"START_LINE_NUMBER":87,"AST_CLASS":"Name","LENGTH":1,"START_CHARACTER":2343,"VERSION":1,"LABEL":"W","DATA_TYPE":"nothing","END_LINE_NUMBER":87},{"END_CHARACTER":2021,"START_LINE_NUMBER":81,"AST_CLASS":"Num","LENGTH":1,"START_CHARACTER":2020,"VERSION":1,"LABEL":"L","DATA_TYPE":"number","END_LINE_NUMBER":81},{"END_CHARACTER":2359,"START_LINE_NUMBER":87,"AST_CLASS":"Assign","LENGTH":3,"START_CHARACTER":2319,"VERSION":1,"LABEL":"½","DATA_TYPE":null,"END_LINE_NUMBER":87},{"END_CHARACTER":2158,"START_LINE_NUMBER":83,"AST_CLASS":"Name","LENGTH":4,"START_CHARACTER":2154,"VERSION":0,"LABEL":"W","DATA_TYPE":"Any","END_LINE_NUMBER":83},{"END_CHARACTER":2115,"START_LINE_NUMBER":82,"AST_CLASS":"Name","LENGTH":1,"START_CHARACTER":2114,"VERSION":1,"LABEL":"W","DATA_TYPE":"Any","END_LINE_NUMBER":82},{"END_CHARACTER":2032,"START_LINE_NUMBER":81,"AST_CLASS":"Assign","LENGTH":9,"START_CHARACTER":1990,"VERSION":1,"LABEL":"½","DATA_TYPE":null,"END_LINE_NUMBER":81},{"END_CHARACTER":2312,"START_LINE_NUMBER":86,"AST_CLASS":"Name","LENGTH":36,"START_CHARACTER":2276,"VERSION":0,"LABEL":"W","DATA_TYPE":"","END_LINE_NUMBER":86},{"END_CHARACTER":0,"START_LINE_NUMBER":0,"AST_CLASS":"Name","LENGTH":0,"START_CHARACTER":0,"VERSION":0,"LABEL":"W","DATA_TYPE":"Any","END_LINE_NUMBER":0},{"END_CHARACTER":2453,"START_LINE_NUMBER":88,"AST_CLASS":"Name","LENGTH":1,"START_CHARACTER":2452,"VERSION":0,"LABEL":"W","DATA_TYPE":"Any","END_LINE_NUMBER":88},{"END_CHARACTER":2048,"START_LINE_NUMBER":82,"AST_CLASS":"Name","LENGTH":1,"START_CHARACTER":2047,"VERSION":1,"LABEL":"W","DATA_TYPE":"nothing","END_LINE_NUMBER":82},{"END_CHARACTER":2199,"START_LINE_NUMBER":83,"AST_CLASS":"Str","LENGTH":22,"START_CHARACTER":2177,"VERSION":0,"LABEL":"B","DATA_TYPE":"String","END_LINE_NUMBER":83},{"END_CHARACTER":2259,"START_LINE_NUMBER":85,"AST_CLASS":"Call","LENGTH":4,"START_CHARACTER":2200,"VERSION":1,"LABEL":"function.map()","DATA_TYPE":"function.map()","END_LINE_NUMBER":85},{"END_CHARACTER":1987,"START_LINE_NUMBER":79,"AST_CLASS":"Assign","LENGTH":3,"START_CHARACTER":1939,"VERSION":0,"LABEL":"½","DATA_TYPE":null,"END_LINE_NUMBER":79},{"END_CHARACTER":0,"START_LINE_NUMBER":0,"AST_CLASS":"Name","LENGTH":0,"START_CHARACTER":0,"VERSION":0,"LABEL":"W","DATA_TYPE":"Any","END_LINE_NUMBER":0},{"END_CHARACTER":1987,"START_LINE_NUMBER":79,"AST_CLASS":"Call","LENGTH":10,"START_CHARACTER":1942,"VERSION":0,"LABEL":"function.rearrange()","DATA_TYPE":"function.rearrange()","END_LINE_NUMBER":79},{"END_CHARACTER":2042,"START_LINE_NUMBER":82,"AST_CLASS":"Name","LENGTH":1,"START_CHARACTER":2041,"VERSION":1,"LABEL":"W","DATA_TYPE":"nothing","END_LINE_NUMBER":82},{"END_CHARACTER":2145,"START_LINE_NUMBER":82,"AST_CLASS":"Assign","LENGTH":3,"START_CHARACTER":2105,"VERSION":0,"LABEL":"½","DATA_TYPE":null,"END_LINE_NUMBER":82},{"END_CHARACTER":2175,"START_LINE_NUMBER":83,"AST_CLASS":"Name","LENGTH":4,"START_CHARACTER":2171,"VERSION":0,"LABEL":"W","DATA_TYPE":"Any","END_LINE_NUMBER":83},{"END_CHARACTER":2254,"START_LINE_NUMBER":85,"AST_CLASS":"Name","LENGTH":1,"START_CHARACTER":2253,"VERSION":1,"LABEL":"W","DATA_TYPE":"nothing","END_LINE_NUMBER":85},{"END_CHARACTER":0,"START_LINE_NUMBER":0,"AST_CLASS":"Name","LENGTH":0,"START_CHARACTER":0,"VERSION":1,"LABEL":"W","DATA_TYPE":"Any","END_LINE_NUMBER":0},{"END_CHARACTER":2112,"START_LINE_NUMBER":82,"AST_CLASS":"Name","LENGTH":1,"START_CHARACTER":2111,"VERSION":1,"LABEL":"W","DATA_TYPE":"Any","END_LINE_NUMBER":82},{"END_CHARACTER":2301,"START_LINE_NUMBER":86,"AST_CLASS":"Num","LENGTH":1,"START_CHARACTER":2300,"VERSION":0,"LABEL":"L","DATA_TYPE":"number","END_LINE_NUMBER":86},{"END_CHARACTER":0,"START_LINE_NUMBER":0,"AST_CLASS":"Name","LENGTH":0,"START_CHARACTER":0,"VERSION":1,"LABEL":"W","DATA_TYPE":"Any","END_LINE_NUMBER":0},{"END_CHARACTER":1888,"START_LINE_NUMBER":78,"AST_CLASS":"Name","LENGTH":12,"START_CHARACTER":1876,"VERSION":1,"LABEL":"W","DATA_TYPE":"Any","END_LINE_NUMBER":78},{"END_CHARACTER":2274,"START_LINE_NUMBER":86,"AST_CLASS":"Call","LENGTH":10,"START_CHARACTER":2262,"VERSION":0,"LABEL":"to_q()","DATA_TYPE":"to_q()","END_LINE_NUMBER":86},{"END_CHARACTER":2269,"START_LINE_NUMBER":86,"AST_CLASS":"Name","LENGTH":1,"START_CHARACTER":2268,"VERSION":1,"LABEL":"W","DATA_TYPE":"nothing","END_LINE_NUMBER":86},{"END_CHARACTER":2194,"START_LINE_NUMBER":85,"AST_CLASS":"Tuple","LENGTH":3,"START_CHARACTER":2194,"VERSION":1,"LABEL":"()","DATA_TYPE":"()","END_LINE_NUMBER":85},{"END_CHARACTER":0,"START_LINE_NUMBER":0,"AST_CLASS":"Name","LENGTH":0,"START_CHARACTER":0,"VERSION":0,"LABEL":"W","DATA_TYPE":"Any","END_LINE_NUMBER":0},{"END_CHARACTER":2454,"START_LINE_NUMBER":88,"AST_CLASS":"Tuple","LENGTH":3,"START_CHARACTER":2450,"VERSION":0,"LABEL":"()","DATA_TYPE":"()","END_LINE_NUMBER":88},{"END_CHARACTER":2266,"START_LINE_NUMBER":86,"AST_CLASS":"Name","LENGTH":4,"START_CHARACTER":2262,"VERSION":0,"LABEL":"W","DATA_TYPE":"AdjacentAttention","END_LINE_NUMBER":86},{"END_CHARACTER":2012,"START_LINE_NUMBER":81,"AST_CLASS":"Name","LENGTH":1,"START_CHARACTER":2011,"VERSION":1,"LABEL":"W","DATA_TYPE":"Any","END_LINE_NUMBER":81},{"END_CHARACTER":2130,"START_LINE_NUMBER":82,"AST_CLASS":"Name","LENGTH":1,"START_CHARACTER":2129,"VERSION":0,"LABEL":"W","DATA_TYPE":"Any","END_LINE_NUMBER":82},{"END_CHARACTER":2145,"START_LINE_NUMBER":82,"AST_CLASS":"Call","LENGTH":21,"START_CHARACTER":2108,"VERSION":0,"LABEL":"function.batched_index_select()","DATA_TYPE":"function.batched_index_select()","END_LINE_NUMBER":82},{"END_CHARACTER":2258,"START_LINE_NUMBER":85,"AST_CLASS":"Tuple","LENGTH":3,"START_CHARACTER":2254,"VERSION":1,"LABEL":"()","DATA_TYPE":"()","END_LINE_NUMBER":85},{"END_CHARACTER":2207,"START_LINE_NUMBER":83,"AST_CLASS":"Call","LENGTH":10,"START_CHARACTER":2161,"VERSION":0,"LABEL":"function.rearrange()","DATA_TYPE":"function.rearrange()","END_LINE_NUMBER":83},{"END_CHARACTER":2319,"START_LINE_NUMBER":87,"AST_CLASS":"Name","LENGTH":1,"START_CHARACTER":2318,"VERSION":1,"LABEL":"W","DATA_TYPE":"nothing","END_LINE_NUMBER":87},{"END_CHARACTER":2118,"START_LINE_NUMBER":82,"AST_CLASS":"Name","LENGTH":1,"START_CHARACTER":2117,"VERSION":1,"LABEL":"W","DATA_TYPE":"Any","END_LINE_NUMBER":82},{"END_CHARACTER":2197,"START_LINE_NUMBER":85,"AST_CLASS":"Name","LENGTH":1,"START_CHARACTER":2196,"VERSION":1,"LABEL":"W","DATA_TYPE":"nothing","END_LINE_NUMBER":85},{"END_CHARACTER":2292,"START_LINE_NUMBER":86,"AST_CLASS":"Name","LENGTH":4,"START_CHARACTER":2288,"VERSION":0,"LABEL":"W","DATA_TYPE":"Any","END_LINE_NUMBER":86},{"END_CHARACTER":1912,"START_LINE_NUMBER":78,"AST_CLASS":"Name","LENGTH":14,"START_CHARACTER":1898,"VERSION":1,"LABEL":"W","DATA_TYPE":"Any","END_LINE_NUMBER":78},{"END_CHARACTER":0,"START_LINE_NUMBER":0,"AST_CLASS":"Name","LENGTH":0,"START_CHARACTER":0,"VERSION":0,"LABEL":"W","DATA_TYPE":"","END_LINE_NUMBER":0},{"END_CHARACTER":2194,"START_LINE_NUMBER":85,"AST_CLASS":"Name","LENGTH":1,"START_CHARACTER":2193,"VERSION":1,"LABEL":"W","DATA_TYPE":"nothing","END_LINE_NUMBER":85},{"END_CHARACTER":1966,"START_LINE_NUMBER":79,"AST_CLASS":"Name","LENGTH":14,"START_CHARACTER":1952,"VERSION":0,"LABEL":"W","DATA_TYPE":"Any","END_LINE_NUMBER":79},{"END_CHARACTER":2259,"START_LINE_NUMBER":85,"AST_CLASS":"Assign","LENGTH":6,"START_CHARACTER":2194,"VERSION":1,"LABEL":"½","DATA_TYPE":null,"END_LINE_NUMBER":85},{"END_CHARACTER":2105,"START_LINE_NUMBER":82,"AST_CLASS":"Name","LENGTH":4,"START_CHARACTER":2101,"VERSION":0,"LABEL":"W","DATA_TYPE":"Any","END_LINE_NUMBER":82},{"END_CHARACTER":0,"START_LINE_NUMBER":0,"AST_CLASS":"Name","LENGTH":0,"START_CHARACTER":0,"VERSION":0,"LABEL":"W","DATA_TYPE":"Any","END_LINE_NUMBER":0},{"END_CHARACTER":2312,"START_LINE_NUMBER":86,"AST_CLASS":"Call","LENGTH":23,"START_CHARACTER":2277,"VERSION":0,"LABEL":"chunk()","DATA_TYPE":"chunk()","END_LINE_NUMBER":86},{"END_CHARACTER":2309,"START_LINE_NUMBER":86,"AST_CLASS":"Assign","LENGTH":3,"START_CHARACTER":2269,"VERSION":1,"LABEL":"½","DATA_TYPE":null,"END_LINE_NUMBER":86},{"END_CHARACTER":2368,"START_LINE_NUMBER":87,"AST_CLASS":"Assign","LENGTH":3,"START_CHARACTER":2322,"VERSION":0,"LABEL":"½","DATA_TYPE":null,"END_LINE_NUMBER":87},{"END_CHARACTER":0,"START_LINE_NUMBER":0,"AST_CLASS":"Name","LENGTH":0,"START_CHARACTER":0,"VERSION":0,"LABEL":"W","DATA_TYPE":"Any","END_LINE_NUMBER":0},{"END_CHARACTER":2452,"START_LINE_NUMBER":88,"AST_CLASS":"Name","LENGTH":1,"START_CHARACTER":2451,"VERSION":1,"LABEL":"W","DATA_TYPE":"nothing","END_LINE_NUMBER":88},{"END_CHARACTER":2045,"START_LINE_NUMBER":82,"AST_CLASS":"Name","LENGTH":1,"START_CHARACTER":2044,"VERSION":1,"LABEL":"W","DATA_TYPE":"nothing","END_LINE_NUMBER":82},{"END_CHARACTER":2453,"START_LINE_NUMBER":88,"AST_CLASS":"Tuple","LENGTH":3,"START_CHARACTER":2449,"VERSION":1,"LABEL":"()","DATA_TYPE":"()","END_LINE_NUMBER":88},{"END_CHARACTER":1986,"START_LINE_NUMBER":79,"AST_CLASS":"Str","LENGTH":18,"START_CHARACTER":1968,"VERSION":0,"LABEL":"B","DATA_TYPE":"String","END_LINE_NUMBER":79},{"END_CHARACTER":0,"START_LINE_NUMBER":0,"AST_CLASS":"Name","LENGTH":0,"START_CHARACTER":0,"VERSION":0,"LABEL":"W","DATA_TYPE":"AdjacentAttention","END_LINE_NUMBER":0}],"COMMITTER_NAME":"Phil Wang","LINK":"https:\/\/github.com\/lucidrains\/adjacent-attention-network\/commit\/3cf88ab92090fcbd2ab52d98b83172b5e8e4b3fe#diff-71f2ddd08dfbd4dae492be6a13060eb54c6e79f8b54246b5f612c2e7c269ab4fL72","COMMIT_NAME":"3cf88ab92090fcbd2ab52d98b83172b5e8e4b3fe","AUTHOR_EMAIL":"lucidrains@gmail.com","N FILE_NAME":"adjacent_attention_network\/adjacent_attention_network.py","M CLASS_NAME":"AdjacentAttention","N METHOD_NAME":"forward(4)","START_LINE_BEFORE_CODE":79,"M METHOD_NAME":"forward(4)","PARENT_CLASS":"nn.Module","END_LINE_BEFORE_CODE":88,"END_CHARACTER_BEFORE_CODE":2455,"TIME":"2020-12-14","AUTHOR_NAME":"Phil Wang","START_CHARACTER_BEFORE_CODE":1927,"END_LINE_AFTER_CODE":88,"N CLASS_NAME":"AdjacentAttention","FRAGMENT_ID":4347342,"END_CHARACTER_AFTER_CODE":2454,"START_CHARACTER_AFTER_CODE":1876},{"M FILE_NAME":"gsa_pytorch\/gsa_pytorch.py","PROJECT_NAME":"lucidrains\/global-self-attention-network","COMMITTER_EMAIL":"lucidrains@gmail.com","START_LINE_AFTER_CODE":57,"NODE_INFO":[{"END_CHARACTER":0,"START_LINE_NUMBER":0,"AST_CLASS":"Name","LENGTH":0,"START_CHARACTER":0,"VERSION":1,"LABEL":"W","DATA_TYPE":"Any","END_LINE_NUMBER":0},{"END_CHARACTER":2779,"START_LINE_NUMBER":79,"AST_CLASS":"Call","LENGTH":45,"START_CHARACTER":2734,"VERSION":1,"LABEL":"contiguous()","DATA_TYPE":"contiguous()","END_LINE_NUMBER":79},{"END_CHARACTER":2109,"START_LINE_NUMBER":63,"AST_CLASS":"Tuple","LENGTH":3,"START_CHARACTER":2109,"VERSION":1,"LABEL":"()","DATA_TYPE":"()","END_LINE_NUMBER":63},{"END_CHARACTER":2731,"START_LINE_NUMBER":79,"AST_CLASS":"Name","LENGTH":11,"START_CHARACTER":2720,"VERSION":1,"LABEL":"W","DATA_TYPE":"Any","END_LINE_NUMBER":79},{"END_CHARACTER":2648,"START_LINE_NUMBER":78,"AST_CLASS":"Str","LENGTH":28,"START_CHARACTER":2620,"VERSION":0,"LABEL":"B","DATA_TYPE":"String","END_LINE_NUMBER":78},{"END_CHARACTER":2762,"START_LINE_NUMBER":79,"AST_CLASS":"Name","LENGTH":1,"START_CHARACTER":2761,"VERSION":1,"LABEL":"W","DATA_TYPE":"Any","END_LINE_NUMBER":79},{"END_CHARACTER":2594,"START_LINE_NUMBER":78,"AST_CLASS":"Name","LENGTH":11,"START_CHARACTER":2583,"VERSION":0,"LABEL":"W","DATA_TYPE":"Any","END_LINE_NUMBER":78},{"END_CHARACTER":2618,"START_LINE_NUMBER":78,"AST_CLASS":"Name","LENGTH":11,"START_CHARACTER":2607,"VERSION":0,"LABEL":"W","DATA_TYPE":"Any","END_LINE_NUMBER":78},{"END_CHARACTER":2292,"START_LINE_NUMBER":70,"AST_CLASS":"Name","LENGTH":2,"START_CHARACTER":2290,"VERSION":0,"LABEL":"W","DATA_TYPE":"Any","END_LINE_NUMBER":70},{"END_CHARACTER":2109,"START_LINE_NUMBER":63,"AST_CLASS":"Name","LENGTH":1,"START_CHARACTER":2108,"VERSION":1,"LABEL":"W","DATA_TYPE":"nothing","END_LINE_NUMBER":63},{"END_CHARACTER":2029,"START_LINE_NUMBER":62,"AST_CLASS":"Name","LENGTH":2,"START_CHARACTER":2027,"VERSION":0,"LABEL":"W","DATA_TYPE":"Any","END_LINE_NUMBER":62},{"END_CHARACTER":2188,"START_LINE_NUMBER":63,"AST_CLASS":"Call","LENGTH":4,"START_CHARACTER":2115,"VERSION":1,"LABEL":"function.map()","DATA_TYPE":"function.map()","END_LINE_NUMBER":63},{"END_CHARACTER":1874,"START_LINE_NUMBER":58,"AST_CLASS":"Name","LENGTH":11,"START_CHARACTER":1863,"VERSION":1,"LABEL":"W","DATA_TYPE":"Any","END_LINE_NUMBER":58},{"END_CHARACTER":1898,"START_LINE_NUMBER":58,"AST_CLASS":"Name","LENGTH":11,"START_CHARACTER":1887,"VERSION":1,"LABEL":"W","DATA_TYPE":"Any","END_LINE_NUMBER":58},{"END_CHARACTER":1809,"START_LINE_NUMBER":57,"AST_CLASS":"Name","LENGTH":11,"START_CHARACTER":1798,"VERSION":0,"LABEL":"W","DATA_TYPE":"Any","END_LINE_NUMBER":57},{"END_CHARACTER":2765,"START_LINE_NUMBER":79,"AST_CLASS":"Name","LENGTH":1,"START_CHARACTER":2764,"VERSION":1,"LABEL":"W","DATA_TYPE":"Any","END_LINE_NUMBER":79},{"END_CHARACTER":2779,"START_LINE_NUMBER":79,"AST_CLASS":"Assign","LENGTH":3,"START_CHARACTER":2731,"VERSION":1,"LABEL":"½","DATA_TYPE":null,"END_LINE_NUMBER":79},{"END_CHARACTER":2244,"START_LINE_NUMBER":66,"AST_CLASS":"Name","LENGTH":2,"START_CHARACTER":2242,"VERSION":0,"LABEL":"W","DATA_TYPE":"Any","END_LINE_NUMBER":66},{"END_CHARACTER":2112,"START_LINE_NUMBER":63,"AST_CLASS":"Name","LENGTH":1,"START_CHARACTER":2111,"VERSION":1,"LABEL":"W","DATA_TYPE":"nothing","END_LINE_NUMBER":63},{"END_CHARACTER":2520,"START_LINE_NUMBER":74,"AST_CLASS":"Delete","LENGTH":6,"START_CHARACTER":2514,"VERSION":0,"LABEL":"delete","DATA_TYPE":null,"END_LINE_NUMBER":74},{"END_CHARACTER":1809,"START_LINE_NUMBER":57,"AST_CLASS":"Name","LENGTH":11,"START_CHARACTER":1798,"VERSION":1,"LABEL":"W","DATA_TYPE":"Any","END_LINE_NUMBER":57},{"END_CHARACTER":2755,"START_LINE_NUMBER":79,"AST_CLASS":"Name","LENGTH":1,"START_CHARACTER":2754,"VERSION":1,"LABEL":"W","DATA_TYPE":"Any","END_LINE_NUMBER":79},{"END_CHARACTER":2663,"START_LINE_NUMBER":78,"AST_CLASS":"Call","LENGTH":10,"START_CHARACTER":2597,"VERSION":0,"LABEL":"function.rearrange()","DATA_TYPE":"function.rearrange()","END_LINE_NUMBER":78},{"END_CHARACTER":2766,"START_LINE_NUMBER":79,"AST_CLASS":"Call","LENGTH":20,"START_CHARACTER":2734,"VERSION":1,"LABEL":"reshape()","DATA_TYPE":"reshape()","END_LINE_NUMBER":79},{"END_CHARACTER":2188,"START_LINE_NUMBER":63,"AST_CLASS":"Assign","LENGTH":6,"START_CHARACTER":2109,"VERSION":1,"LABEL":"½","DATA_TYPE":null,"END_LINE_NUMBER":63},{"END_CHARACTER":2183,"START_LINE_NUMBER":63,"AST_CLASS":"Name","LENGTH":1,"START_CHARACTER":2182,"VERSION":1,"LABEL":"W","DATA_TYPE":"Any","END_LINE_NUMBER":63},{"END_CHARACTER":2663,"START_LINE_NUMBER":78,"AST_CLASS":"Assign","LENGTH":3,"START_CHARACTER":2594,"VERSION":0,"LABEL":"½","DATA_TYPE":null,"END_LINE_NUMBER":78},{"END_CHARACTER":0,"START_LINE_NUMBER":0,"AST_CLASS":"Name","LENGTH":0,"START_CHARACTER":0,"VERSION":1,"LABEL":"W","DATA_TYPE":"nothing","END_LINE_NUMBER":0},{"END_CHARACTER":1937,"START_LINE_NUMBER":58,"AST_CLASS":"Assign","LENGTH":3,"START_CHARACTER":1874,"VERSION":1,"LABEL":"½","DATA_TYPE":null,"END_LINE_NUMBER":58},{"END_CHARACTER":2244,"START_LINE_NUMBER":66,"AST_CLASS":"Delete","LENGTH":6,"START_CHARACTER":2238,"VERSION":0,"LABEL":"delete","DATA_TYPE":null,"END_LINE_NUMBER":66},{"END_CHARACTER":2520,"START_LINE_NUMBER":74,"AST_CLASS":"Name","LENGTH":2,"START_CHARACTER":2518,"VERSION":0,"LABEL":"W","DATA_TYPE":"Any","END_LINE_NUMBER":74},{"END_CHARACTER":2759,"START_LINE_NUMBER":79,"AST_CLASS":"Num","LENGTH":2,"START_CHARACTER":2757,"VERSION":1,"LABEL":"L","DATA_TYPE":"number","END_LINE_NUMBER":79},{"END_CHARACTER":2745,"START_LINE_NUMBER":79,"AST_CLASS":"Name","LENGTH":11,"START_CHARACTER":2734,"VERSION":1,"LABEL":"W","DATA_TYPE":"Any","END_LINE_NUMBER":79},{"END_CHARACTER":1922,"START_LINE_NUMBER":58,"AST_CLASS":"Str","LENGTH":22,"START_CHARACTER":1900,"VERSION":1,"LABEL":"B","DATA_TYPE":"String","END_LINE_NUMBER":58},{"END_CHARACTER":0,"START_LINE_NUMBER":0,"AST_CLASS":"Name","LENGTH":0,"START_CHARACTER":0,"VERSION":1,"LABEL":"W","DATA_TYPE":"Any","END_LINE_NUMBER":0},{"END_CHARACTER":2545,"START_LINE_NUMBER":76,"AST_CLASS":"Name","LENGTH":11,"START_CHARACTER":2534,"VERSION":0,"LABEL":"W","DATA_TYPE":"Any","END_LINE_NUMBER":76},{"END_CHARACTER":1937,"START_LINE_NUMBER":58,"AST_CLASS":"Call","LENGTH":10,"START_CHARACTER":1877,"VERSION":1,"LABEL":"function.rearrange()","DATA_TYPE":"function.rearrange()","END_LINE_NUMBER":58},{"END_CHARACTER":0,"START_LINE_NUMBER":0,"AST_CLASS":"Name","LENGTH":0,"START_CHARACTER":0,"VERSION":1,"LABEL":"W","DATA_TYPE":"Any","END_LINE_NUMBER":0},{"END_CHARACTER":2187,"START_LINE_NUMBER":63,"AST_CLASS":"Tuple","LENGTH":3,"START_CHARACTER":2183,"VERSION":1,"LABEL":"()","DATA_TYPE":"()","END_LINE_NUMBER":63},{"END_CHARACTER":0,"START_LINE_NUMBER":0,"AST_CLASS":"Name","LENGTH":0,"START_CHARACTER":0,"VERSION":1,"LABEL":"W","DATA_TYPE":"Any","END_LINE_NUMBER":0},{"END_CHARACTER":2682,"START_LINE_NUMBER":77,"AST_CLASS":"Name","LENGTH":11,"START_CHARACTER":2671,"VERSION":1,"LABEL":"W","DATA_TYPE":"Any","END_LINE_NUMBER":77},{"END_CHARACTER":2186,"START_LINE_NUMBER":63,"AST_CLASS":"Name","LENGTH":1,"START_CHARACTER":2185,"VERSION":1,"LABEL":"W","DATA_TYPE":"Any","END_LINE_NUMBER":63}],"COMMITTER_NAME":"Phil Wang","LINK":"https:\/\/github.com\/lucidrains\/global-self-attention-network\/commit\/bb923ca7de188475568a799120af2d7985efa6ed#diff-af8f87d68d6adf627dabaab6519f02d4b454d6ba08e146c8f5dc18f07e073e31L46","COMMIT_NAME":"bb923ca7de188475568a799120af2d7985efa6ed","AUTHOR_EMAIL":"lucidrains@gmail.com","N FILE_NAME":"gsa_pytorch\/gsa_pytorch.py","M CLASS_NAME":"GSA","N METHOD_NAME":"forward(2)","START_LINE_BEFORE_CODE":57,"M METHOD_NAME":"forward(2)","PARENT_CLASS":"nn.Module","END_LINE_BEFORE_CODE":78,"END_CHARACTER_BEFORE_CODE":2663,"TIME":"2020-10-05","AUTHOR_NAME":"Phil Wang","START_CHARACTER_BEFORE_CODE":1798,"END_LINE_AFTER_CODE":79,"N CLASS_NAME":"GSA","FRAGMENT_ID":4347343,"END_CHARACTER_AFTER_CODE":2779,"START_CHARACTER_AFTER_CODE":1798},{"M FILE_NAME":"dalle_pytorch\/attention.py","PROJECT_NAME":"lucidrains\/dalle-pytorch","COMMITTER_EMAIL":"lucidrains@gmail.com","START_LINE_AFTER_CODE":129,"NODE_INFO":[{"END_CHARACTER":6789,"START_LINE_NUMBER":190,"AST_CLASS":"Name","LENGTH":11,"START_CHARACTER":6778,"VERSION":0,"LABEL":"W","DATA_TYPE":"Any","END_LINE_NUMBER":190},{"END_CHARACTER":5900,"START_LINE_NUMBER":172,"AST_CLASS":"Name","LENGTH":5,"START_CHARACTER":5895,"VERSION":1,"LABEL":"W","DATA_TYPE":"nothing","END_LINE_NUMBER":172},{"END_CHARACTER":6632,"START_LINE_NUMBER":185,"AST_CLASS":"Name","LENGTH":13,"START_CHARACTER":6619,"VERSION":0,"LABEL":"W","DATA_TYPE":"Any","END_LINE_NUMBER":185},{"END_CHARACTER":0,"START_LINE_NUMBER":0,"AST_CLASS":"Name","LENGTH":0,"START_CHARACTER":0,"VERSION":1,"LABEL":"W","DATA_TYPE":"nothing","END_LINE_NUMBER":0},{"END_CHARACTER":6822,"START_LINE_NUMBER":190,"AST_CLASS":"Assign","LENGTH":4,"START_CHARACTER":6789,"VERSION":0,"LABEL":"½","DATA_TYPE":null,"END_LINE_NUMBER":190},{"END_CHARACTER":6732,"START_LINE_NUMBER":189,"AST_CLASS":"Name","LENGTH":13,"START_CHARACTER":6719,"VERSION":0,"LABEL":"W","DATA_TYPE":"Any","END_LINE_NUMBER":189},{"END_CHARACTER":5592,"START_LINE_NUMBER":167,"AST_CLASS":"Name","LENGTH":7,"START_CHARACTER":5585,"VERSION":0,"LABEL":"W","DATA_TYPE":"Any","END_LINE_NUMBER":167},{"END_CHARACTER":6768,"START_LINE_NUMBER":189,"AST_CLASS":"Str","LENGTH":14,"START_CHARACTER":6754,"VERSION":0,"LABEL":"B","DATA_TYPE":"String","END_LINE_NUMBER":189},{"END_CHARACTER":6752,"START_LINE_NUMBER":189,"AST_CLASS":"Name","LENGTH":7,"START_CHARACTER":6745,"VERSION":0,"LABEL":"W","DATA_TYPE":"Any","END_LINE_NUMBER":189},{"END_CHARACTER":6896,"START_LINE_NUMBER":191,"AST_CLASS":"Name","LENGTH":11,"START_CHARACTER":6885,"VERSION":1,"LABEL":"W","DATA_TYPE":"Any","END_LINE_NUMBER":191},{"END_CHARACTER":6587,"START_LINE_NUMBER":185,"AST_CLASS":"Name","LENGTH":14,"START_CHARACTER":6573,"VERSION":1,"LABEL":"W","DATA_TYPE":"Tuple[Any, int, Any, int]","END_LINE_NUMBER":185},{"END_CHARACTER":5669,"START_LINE_NUMBER":168,"AST_CLASS":"BinOp","LENGTH":3,"START_CHARACTER":5665,"VERSION":1,"LABEL":"á","DATA_TYPE":null,"END_LINE_NUMBER":168},{"END_CHARACTER":5669,"START_LINE_NUMBER":168,"AST_CLASS":"Num","LENGTH":1,"START_CHARACTER":5668,"VERSION":1,"LABEL":"L","DATA_TYPE":"number","END_LINE_NUMBER":168},{"END_CHARACTER":6822,"START_LINE_NUMBER":190,"AST_CLASS":"Compare","LENGTH":29,"START_CHARACTER":6793,"VERSION":0,"LABEL":"ò","DATA_TYPE":null,"END_LINE_NUMBER":190},{"END_CHARACTER":5665,"START_LINE_NUMBER":168,"AST_CLASS":"Name","LENGTH":12,"START_CHARACTER":5653,"VERSION":1,"LABEL":"W","DATA_TYPE":"Any","END_LINE_NUMBER":168},{"END_CHARACTER":5893,"START_LINE_NUMBER":172,"AST_CLASS":"Tuple","LENGTH":7,"START_CHARACTER":5893,"VERSION":1,"LABEL":"()","DATA_TYPE":"()","END_LINE_NUMBER":172},{"END_CHARACTER":5597,"START_LINE_NUMBER":167,"AST_CLASS":"Name","LENGTH":12,"START_CHARACTER":5585,"VERSION":1,"LABEL":"W","DATA_TYPE":"Any","END_LINE_NUMBER":167},{"END_CHARACTER":6896,"START_LINE_NUMBER":191,"AST_CLASS":"Compare","LENGTH":28,"START_CHARACTER":6868,"VERSION":1,"LABEL":"ò","DATA_TYPE":null,"END_LINE_NUMBER":191},{"END_CHARACTER":6454,"START_LINE_NUMBER":183,"AST_CLASS":"BinOp","LENGTH":3,"START_CHARACTER":6450,"VERSION":0,"LABEL":"á","DATA_TYPE":null,"END_LINE_NUMBER":183},{"END_CHARACTER":5690,"START_LINE_NUMBER":168,"AST_CLASS":"BinOp","LENGTH":3,"START_CHARACTER":5686,"VERSION":1,"LABEL":"á","DATA_TYPE":null,"END_LINE_NUMBER":168},{"END_CHARACTER":6864,"START_LINE_NUMBER":191,"AST_CLASS":"Name","LENGTH":12,"START_CHARACTER":6852,"VERSION":1,"LABEL":"W","DATA_TYPE":"Any","END_LINE_NUMBER":191},{"END_CHARACTER":6769,"START_LINE_NUMBER":189,"AST_CLASS":"Assign","LENGTH":3,"START_CHARACTER":6732,"VERSION":0,"LABEL":"½","DATA_TYPE":null,"END_LINE_NUMBER":189},{"END_CHARACTER":6262,"START_LINE_NUMBER":181,"AST_CLASS":"Name","LENGTH":7,"START_CHARACTER":6255,"VERSION":0,"LABEL":"W","DATA_TYPE":"Any","END_LINE_NUMBER":181},{"END_CHARACTER":5978,"START_LINE_NUMBER":172,"AST_CLASS":"Tuple","LENGTH":7,"START_CHARACTER":5970,"VERSION":1,"LABEL":"()","DATA_TYPE":"()","END_LINE_NUMBER":172},{"END_CHARACTER":0,"START_LINE_NUMBER":0,"AST_CLASS":"Name","LENGTH":0,"START_CHARACTER":0,"VERSION":1,"LABEL":"W","DATA_TYPE":"nothing","END_LINE_NUMBER":0},{"END_CHARACTER":6822,"START_LINE_NUMBER":190,"AST_CLASS":"Name","LENGTH":13,"START_CHARACTER":6809,"VERSION":0,"LABEL":"W","DATA_TYPE":"Any","END_LINE_NUMBER":190},{"END_CHARACTER":5693,"START_LINE_NUMBER":168,"AST_CLASS":"Num","LENGTH":1,"START_CHARACTER":5692,"VERSION":1,"LABEL":"L","DATA_TYPE":"number","END_LINE_NUMBER":168},{"END_CHARACTER":6896,"START_LINE_NUMBER":191,"AST_CLASS":"Assign","LENGTH":4,"START_CHARACTER":6864,"VERSION":1,"LABEL":"½","DATA_TYPE":null,"END_LINE_NUMBER":191},{"END_CHARACTER":0,"START_LINE_NUMBER":0,"AST_CLASS":"Name","LENGTH":0,"START_CHARACTER":0,"VERSION":1,"LABEL":"W","DATA_TYPE":"Tuple[Any, int, Any, int]","END_LINE_NUMBER":0},{"END_CHARACTER":5977,"START_LINE_NUMBER":172,"AST_CLASS":"Name","LENGTH":5,"START_CHARACTER":5972,"VERSION":1,"LABEL":"W","DATA_TYPE":"nothing","END_LINE_NUMBER":172},{"END_CHARACTER":6448,"START_LINE_NUMBER":183,"AST_CLASS":"Name","LENGTH":7,"START_CHARACTER":6441,"VERSION":0,"LABEL":"W","DATA_TYPE":"Any","END_LINE_NUMBER":183},{"END_CHARACTER":5672,"START_LINE_NUMBER":168,"AST_CLASS":"Num","LENGTH":1,"START_CHARACTER":5671,"VERSION":1,"LABEL":"L","DATA_TYPE":"number","END_LINE_NUMBER":168},{"END_CHARACTER":5686,"START_LINE_NUMBER":168,"AST_CLASS":"Name","LENGTH":12,"START_CHARACTER":5674,"VERSION":1,"LABEL":"W","DATA_TYPE":"Any","END_LINE_NUMBER":168},{"END_CHARACTER":5649,"START_LINE_NUMBER":168,"AST_CLASS":"Name","LENGTH":14,"START_CHARACTER":5635,"VERSION":1,"LABEL":"W","DATA_TYPE":"Tuple[Any, int, Any, int]","END_LINE_NUMBER":168},{"END_CHARACTER":5690,"START_LINE_NUMBER":168,"AST_CLASS":"Num","LENGTH":1,"START_CHARACTER":5689,"VERSION":1,"LABEL":"L","DATA_TYPE":"number","END_LINE_NUMBER":168},{"END_CHARACTER":6454,"START_LINE_NUMBER":183,"AST_CLASS":"Num","LENGTH":1,"START_CHARACTER":6453,"VERSION":0,"LABEL":"L","DATA_TYPE":"number","END_LINE_NUMBER":183},{"END_CHARACTER":5979,"START_LINE_NUMBER":172,"AST_CLASS":"Assign","LENGTH":10,"START_CHARACTER":5893,"VERSION":1,"LABEL":"½","DATA_TYPE":null,"END_LINE_NUMBER":172},{"END_CHARACTER":5893,"START_LINE_NUMBER":172,"AST_CLASS":"Name","LENGTH":5,"START_CHARACTER":5888,"VERSION":1,"LABEL":"W","DATA_TYPE":"nothing","END_LINE_NUMBER":172},{"END_CHARACTER":6806,"START_LINE_NUMBER":190,"AST_CLASS":"Name","LENGTH":13,"START_CHARACTER":6793,"VERSION":0,"LABEL":"W","DATA_TYPE":"Any","END_LINE_NUMBER":190},{"END_CHARACTER":4322,"START_LINE_NUMBER":129,"AST_CLASS":"Name","LENGTH":11,"START_CHARACTER":4311,"VERSION":1,"LABEL":"W","DATA_TYPE":"Any","END_LINE_NUMBER":129},{"END_CHARACTER":6769,"START_LINE_NUMBER":189,"AST_CLASS":"Call","LENGTH":10,"START_CHARACTER":6735,"VERSION":0,"LABEL":"function.rearrange()","DATA_TYPE":"function.rearrange()","END_LINE_NUMBER":189},{"END_CHARACTER":5970,"START_LINE_NUMBER":172,"AST_CLASS":"Name","LENGTH":5,"START_CHARACTER":5965,"VERSION":1,"LABEL":"W","DATA_TYPE":"nothing","END_LINE_NUMBER":172},{"END_CHARACTER":5649,"START_LINE_NUMBER":168,"AST_CLASS":"Name","LENGTH":14,"START_CHARACTER":5635,"VERSION":1,"LABEL":"W","DATA_TYPE":"Tuple[Any, int, Any, int]","END_LINE_NUMBER":168},{"END_CHARACTER":6450,"START_LINE_NUMBER":183,"AST_CLASS":"Tuple","LENGTH":0,"START_CHARACTER":6448,"VERSION":0,"LABEL":"()","DATA_TYPE":"()","END_LINE_NUMBER":183},{"END_CHARACTER":5694,"START_LINE_NUMBER":168,"AST_CLASS":"Tuple","LENGTH":24,"START_CHARACTER":5669,"VERSION":1,"LABEL":"()","DATA_TYPE":"()","END_LINE_NUMBER":168},{"END_CHARACTER":5979,"START_LINE_NUMBER":172,"AST_CLASS":"Call","LENGTH":4,"START_CHARACTER":5903,"VERSION":1,"LABEL":"function.map()","DATA_TYPE":"function.map()","END_LINE_NUMBER":172},{"END_CHARACTER":6765,"START_LINE_NUMBER":187,"AST_CLASS":"Name","LENGTH":13,"START_CHARACTER":6752,"VERSION":1,"LABEL":"W","DATA_TYPE":"Any","END_LINE_NUMBER":187},{"END_CHARACTER":6881,"START_LINE_NUMBER":191,"AST_CLASS":"Name","LENGTH":13,"START_CHARACTER":6868,"VERSION":1,"LABEL":"W","DATA_TYPE":"Any","END_LINE_NUMBER":191}],"COMMITTER_NAME":"Phil Wang","LINK":"https:\/\/github.com\/lucidrains\/dalle-pytorch\/commit\/3064403976ee2fadacef934e789cdd9f4de118ec#diff-58807b9968341c05944b3adf3de1bfcd9d33660121a78f3ef013fd0e9bf16fdfL125","COMMIT_NAME":"3064403976ee2fadacef934e789cdd9f4de118ec","AUTHOR_EMAIL":"lucidrains@gmail.com","N FILE_NAME":"dalle_pytorch\/attention.py","M CLASS_NAME":"SparseConvCausalAttention","N METHOD_NAME":"forward(4)","START_LINE_BEFORE_CODE":167,"M METHOD_NAME":"forward(4)","PARENT_CLASS":"nn.Module","END_LINE_BEFORE_CODE":190,"END_CHARACTER_BEFORE_CODE":6822,"TIME":"2022-03-23","AUTHOR_NAME":"Phil Wang","START_CHARACTER_BEFORE_CODE":5585,"END_LINE_AFTER_CODE":191,"N CLASS_NAME":"SparseConvCausalAttention","FRAGMENT_ID":4347341,"END_CHARACTER_AFTER_CODE":6896,"START_CHARACTER_AFTER_CODE":4311}],"ID":1200,"PATTERN_SIZE":4}