{"PATH":"3\/3401\/details.html","NODES":{"BEFORE_CHANGE":[{"LABEL":"If","DATA_TYPE":null}],"AFTER_CHANGE":[{"LABEL":"dim()","DATA_TYPE":"dim()"},{"LABEL":"BinOp:a","DATA_TYPE":null}]},"NUMBER_OF_REPEATED_NODES":3,"Fragments":[{"M FILE_NAME":"models\/utils.py","PROJECT_NAME":"jintao-huang\/efficientdet_pytorch","COMMITTER_EMAIL":"hjt_study@qq.com","START_LINE_AFTER_CODE":71,"NODE_INFO":[{"END_CHARACTER":2561,"START_LINE_NUMBER":72,"AST_CLASS":"Name","LENGTH":1,"START_CHARACTER":2560,"VERSION":1,"LABEL":"W","DATA_TYPE":"Any","END_LINE_NUMBER":72},{"END_CHARACTER":2593,"START_LINE_NUMBER":73,"AST_CLASS":"Num","LENGTH":1,"START_CHARACTER":2592,"VERSION":0,"LABEL":"L","DATA_TYPE":"number","END_LINE_NUMBER":73},{"END_CHARACTER":2557,"START_LINE_NUMBER":72,"AST_CLASS":"Str","LENGTH":35,"START_CHARACTER":2522,"VERSION":1,"LABEL":"B","DATA_TYPE":"String","END_LINE_NUMBER":72},{"END_CHARACTER":2588,"START_LINE_NUMBER":73,"AST_CLASS":"Call","LENGTH":7,"START_CHARACTER":2581,"VERSION":0,"LABEL":"dim()","DATA_TYPE":"dim()","END_LINE_NUMBER":73},{"END_CHARACTER":2593,"START_LINE_NUMBER":73,"AST_CLASS":"Compare","LENGTH":12,"START_CHARACTER":2581,"VERSION":0,"LABEL":"ò","DATA_TYPE":null,"END_LINE_NUMBER":73},{"END_CHARACTER":2486,"START_LINE_NUMBER":71,"AST_CLASS":"Call","LENGTH":7,"START_CHARACTER":2479,"VERSION":1,"LABEL":"dim()","DATA_TYPE":"dim()","END_LINE_NUMBER":71},{"END_CHARACTER":2491,"START_LINE_NUMBER":71,"AST_CLASS":"Compare","LENGTH":12,"START_CHARACTER":2479,"VERSION":1,"LABEL":"ò","DATA_TYPE":null,"END_LINE_NUMBER":71},{"END_CHARACTER":2567,"START_LINE_NUMBER":72,"AST_CLASS":"BinOp","LENGTH":3,"START_CHARACTER":2557,"VERSION":1,"LABEL":"á","DATA_TYPE":null,"END_LINE_NUMBER":72},{"END_CHARACTER":2736,"START_LINE_NUMBER":73,"AST_CLASS":"If","LENGTH":3,"START_CHARACTER":2578,"VERSION":0,"LABEL":"`","DATA_TYPE":null,"END_LINE_NUMBER":76},{"END_CHARACTER":2491,"START_LINE_NUMBER":71,"AST_CLASS":"Num","LENGTH":1,"START_CHARACTER":2490,"VERSION":1,"LABEL":"L","DATA_TYPE":"number","END_LINE_NUMBER":71},{"END_CHARACTER":2576,"START_LINE_NUMBER":71,"AST_CLASS":"If","LENGTH":3,"START_CHARACTER":2476,"VERSION":1,"LABEL":"`","DATA_TYPE":null,"END_LINE_NUMBER":73},{"END_CHARACTER":0,"START_LINE_NUMBER":0,"AST_CLASS":"Name","LENGTH":0,"START_CHARACTER":0,"VERSION":1,"LABEL":"W","DATA_TYPE":"Any","END_LINE_NUMBER":0},{"END_CHARACTER":2568,"START_LINE_NUMBER":72,"AST_CLASS":"Raise","LENGTH":6,"START_CHARACTER":2505,"VERSION":1,"LABEL":"raise","DATA_TYPE":null,"END_LINE_NUMBER":72},{"END_CHARACTER":2568,"START_LINE_NUMBER":72,"AST_CLASS":"Call","LENGTH":11,"START_CHARACTER":2511,"VERSION":1,"LABEL":"function.ValueError()","DATA_TYPE":"function.ValueError()","END_LINE_NUMBER":72},{"END_CHARACTER":2567,"START_LINE_NUMBER":72,"AST_CLASS":"Call","LENGTH":7,"START_CHARACTER":2560,"VERSION":1,"LABEL":"dim()","DATA_TYPE":"dim()","END_LINE_NUMBER":72}],"COMMITTER_NAME":"Jintao Huang","LINK":"https:\/\/github.com\/jintao-huang\/efficientdet_pytorch\/commit\/f904ad7387726ecd2dac2c099e3f55a9d1a166ef#diff-180d11519347b16a39dbe55e0651b86403aedbf6172aa239536d6610341f0445L71","COMMIT_NAME":"f904ad7387726ecd2dac2c099e3f55a9d1a166ef","AUTHOR_EMAIL":"hjt_study@qq.com","N FILE_NAME":"models\/utils.py","M CLASS_NAME":"FrozenBatchNorm2d","N METHOD_NAME":"forward(2)","START_LINE_BEFORE_CODE":73,"M METHOD_NAME":"forward(2)","PARENT_CLASS":"nn.Module","END_LINE_BEFORE_CODE":76,"END_CHARACTER_BEFORE_CODE":2736,"TIME":"2020-06-09","AUTHOR_NAME":"Jintao Huang","START_CHARACTER_BEFORE_CODE":2578,"END_LINE_AFTER_CODE":73,"N CLASS_NAME":"FrozenBatchNorm2d","FRAGMENT_ID":17489442,"END_CHARACTER_AFTER_CODE":2576,"START_CHARACTER_AFTER_CODE":2476},{"M FILE_NAME":"egs\/wsj0-mix\/danet\/src\/adhoc_criterion.py","PROJECT_NAME":"tky823\/dnn-based_source_separation","COMMITTER_EMAIL":"delta9guitar97@gmail.com","START_LINE_AFTER_CODE":23,"NODE_INFO":[{"END_CHARACTER":714,"START_LINE_NUMBER":26,"AST_CLASS":"Name","LENGTH":4,"START_CHARACTER":710,"VERSION":1,"LABEL":"W","DATA_TYPE":"Union[Tuple[Any, ...], Tuple[()]]","END_LINE_NUMBER":26},{"END_CHARACTER":838,"START_LINE_NUMBER":29,"AST_CLASS":"Subscript","LENGTH":18,"START_CHARACTER":820,"VERSION":1,"LABEL":"[]","DATA_TYPE":"function.sorted()[.]","END_LINE_NUMBER":29},{"END_CHARACTER":665,"START_LINE_NUMBER":23,"AST_CLASS":"Name","LENGTH":4,"START_CHARACTER":661,"VERSION":0,"LABEL":"W","DATA_TYPE":"SquaredError","END_LINE_NUMBER":23},{"END_CHARACTER":1101,"START_LINE_NUMBER":37,"AST_CLASS":"For","LENGTH":4,"START_CHARACTER":1035,"VERSION":1,"LABEL":"k","DATA_TYPE":null,"END_LINE_NUMBER":40},{"END_CHARACTER":1050,"START_LINE_NUMBER":37,"AST_CLASS":"Name","LENGTH":4,"START_CHARACTER":1046,"VERSION":1,"LABEL":"W","DATA_TYPE":"Union[List[Any], List[nothing]]","END_LINE_NUMBER":37},{"END_CHARACTER":0,"START_LINE_NUMBER":0,"AST_CLASS":"Name","LENGTH":0,"START_CHARACTER":0,"VERSION":0,"LABEL":"W","DATA_TYPE":"SquaredError","END_LINE_NUMBER":0},{"END_CHARACTER":1092,"START_LINE_NUMBER":38,"AST_CLASS":"Assign","LENGTH":3,"START_CHARACTER":1068,"VERSION":1,"LABEL":"½","DATA_TYPE":null,"END_LINE_NUMBER":38},{"END_CHARACTER":658,"START_LINE_NUMBER":23,"AST_CLASS":"Name","LENGTH":4,"START_CHARACTER":654,"VERSION":0,"LABEL":"W","DATA_TYPE":"Union[Tuple[Any, ...], Tuple[()]]","END_LINE_NUMBER":23},{"END_CHARACTER":929,"START_LINE_NUMBER":33,"AST_CLASS":"Num","LENGTH":1,"START_CHARACTER":928,"VERSION":0,"LABEL":"L","DATA_TYPE":"number","END_LINE_NUMBER":33},{"END_CHARACTER":1042,"START_LINE_NUMBER":37,"AST_CLASS":"Name","LENGTH":3,"START_CHARACTER":1039,"VERSION":1,"LABEL":"W","DATA_TYPE":"Any","END_LINE_NUMBER":37},{"END_CHARACTER":737,"START_LINE_NUMBER":27,"AST_CLASS":"Name","LENGTH":6,"START_CHARACTER":731,"VERSION":1,"LABEL":"W","DATA_TYPE":"Any","END_LINE_NUMBER":27},{"END_CHARACTER":701,"START_LINE_NUMBER":25,"AST_CLASS":"Assign","LENGTH":3,"START_CHARACTER":688,"VERSION":1,"LABEL":"½","DATA_TYPE":null,"END_LINE_NUMBER":25},{"END_CHARACTER":838,"START_LINE_NUMBER":29,"AST_CLASS":"Assign","LENGTH":3,"START_CHARACTER":817,"VERSION":1,"LABEL":"½","DATA_TYPE":null,"END_LINE_NUMBER":29},{"END_CHARACTER":0,"START_LINE_NUMBER":0,"AST_CLASS":"Name","LENGTH":0,"START_CHARACTER":0,"VERSION":1,"LABEL":"W","DATA_TYPE":"SquaredError","END_LINE_NUMBER":0},{"END_CHARACTER":743,"START_LINE_NUMBER":27,"AST_CLASS":"Name","LENGTH":3,"START_CHARACTER":740,"VERSION":1,"LABEL":"W","DATA_TYPE":"Any","END_LINE_NUMBER":27},{"END_CHARACTER":832,"START_LINE_NUMBER":29,"AST_CLASS":"Call","LENGTH":7,"START_CHARACTER":820,"VERSION":1,"LABEL":"function.sorted()","DATA_TYPE":"function.sorted()","END_LINE_NUMBER":29},{"END_CHARACTER":925,"START_LINE_NUMBER":33,"AST_CLASS":"Call","LENGTH":4,"START_CHARACTER":916,"VERSION":0,"LABEL":"function.len()","DATA_TYPE":"function.len()","END_LINE_NUMBER":33},{"END_CHARACTER":716,"START_LINE_NUMBER":25,"AST_CLASS":"Assign","LENGTH":3,"START_CHARACTER":694,"VERSION":0,"LABEL":"½","DATA_TYPE":null,"END_LINE_NUMBER":25},{"END_CHARACTER":695,"START_LINE_NUMBER":25,"AST_CLASS":"Name","LENGTH":4,"START_CHARACTER":691,"VERSION":1,"LABEL":"W","DATA_TYPE":"Any","END_LINE_NUMBER":25},{"END_CHARACTER":688,"START_LINE_NUMBER":25,"AST_CLASS":"Name","LENGTH":6,"START_CHARACTER":682,"VERSION":1,"LABEL":"W","DATA_TYPE":"Any","END_LINE_NUMBER":25},{"END_CHARACTER":763,"START_LINE_NUMBER":27,"AST_CLASS":"Name","LENGTH":3,"START_CHARACTER":760,"VERSION":1,"LABEL":"W","DATA_TYPE":"Any","END_LINE_NUMBER":27},{"END_CHARACTER":831,"START_LINE_NUMBER":29,"AST_CLASS":"Name","LENGTH":4,"START_CHARACTER":827,"VERSION":1,"LABEL":"W","DATA_TYPE":"Union[List[Any], List[nothing]]","END_LINE_NUMBER":29},{"END_CHARACTER":981,"START_LINE_NUMBER":33,"AST_CLASS":"If","LENGTH":3,"START_CHARACTER":913,"VERSION":0,"LABEL":"`","DATA_TYPE":null,"END_LINE_NUMBER":36},{"END_CHARACTER":924,"START_LINE_NUMBER":33,"AST_CLASS":"Name","LENGTH":4,"START_CHARACTER":920,"VERSION":0,"LABEL":"W","DATA_TYPE":"Union[Tuple[Any, ...], Tuple[()]]","END_LINE_NUMBER":33},{"END_CHARACTER":743,"START_LINE_NUMBER":27,"AST_CLASS":"BinOp","LENGTH":3,"START_CHARACTER":737,"VERSION":1,"LABEL":"á","DATA_TYPE":null,"END_LINE_NUMBER":27},{"END_CHARACTER":837,"START_LINE_NUMBER":29,"AST_CLASS":"Num","LENGTH":3,"START_CHARACTER":834,"VERSION":1,"LABEL":"L","DATA_TYPE":"number","END_LINE_NUMBER":29},{"END_CHARACTER":767,"START_LINE_NUMBER":27,"AST_CLASS":"comprehension","LENGTH":3,"START_CHARACTER":764,"VERSION":1,"LABEL":"-","DATA_TYPE":null,"END_LINE_NUMBER":27},{"END_CHARACTER":680,"START_LINE_NUMBER":23,"AST_CLASS":"Name","LENGTH":19,"START_CHARACTER":661,"VERSION":0,"LABEL":"W","DATA_TYPE":"SquaredError.reduction_dims","END_LINE_NUMBER":23},{"END_CHARACTER":837,"START_LINE_NUMBER":29,"AST_CLASS":"Slice","LENGTH":4,"START_CHARACTER":833,"VERSION":1,"LABEL":"number[.]","DATA_TYPE":"number[.]","END_LINE_NUMBER":29},{"END_CHARACTER":929,"START_LINE_NUMBER":33,"AST_CLASS":"Compare","LENGTH":13,"START_CHARACTER":916,"VERSION":0,"LABEL":"ò","DATA_TYPE":null,"END_LINE_NUMBER":33},{"END_CHARACTER":754,"START_LINE_NUMBER":27,"AST_CLASS":"Num","LENGTH":1,"START_CHARACTER":753,"VERSION":1,"LABEL":"L","DATA_TYPE":"number","END_LINE_NUMBER":27},{"END_CHARACTER":817,"START_LINE_NUMBER":29,"AST_CLASS":"Name","LENGTH":4,"START_CHARACTER":813,"VERSION":1,"LABEL":"W","DATA_TYPE":"Union[List[Any], List[nothing]]","END_LINE_NUMBER":29},{"END_CHARACTER":972,"START_LINE_NUMBER":34,"AST_CLASS":"Assign","LENGTH":3,"START_CHARACTER":947,"VERSION":0,"LABEL":"½","DATA_TYPE":null,"END_LINE_NUMBER":34},{"END_CHARACTER":779,"START_LINE_NUMBER":27,"AST_CLASS":"Name","LENGTH":4,"START_CHARACTER":775,"VERSION":1,"LABEL":"W","DATA_TYPE":"SquaredError","END_LINE_NUMBER":27},{"END_CHARACTER":804,"START_LINE_NUMBER":27,"AST_CLASS":"GeneratorExp","LENGTH":87,"START_CHARACTER":717,"VERSION":1,"LABEL":"7","DATA_TYPE":null,"END_LINE_NUMBER":28},{"END_CHARACTER":650,"START_LINE_NUMBER":23,"AST_CLASS":"Name","LENGTH":4,"START_CHARACTER":646,"VERSION":1,"LABEL":"W","DATA_TYPE":"Any","END_LINE_NUMBER":23},{"END_CHARACTER":794,"START_LINE_NUMBER":27,"AST_CLASS":"Name","LENGTH":19,"START_CHARACTER":775,"VERSION":1,"LABEL":"W","DATA_TYPE":"SquaredError.reduction_dims","END_LINE_NUMBER":27},{"END_CHARACTER":771,"START_LINE_NUMBER":27,"AST_CLASS":"Name","LENGTH":3,"START_CHARACTER":768,"VERSION":1,"LABEL":"W","DATA_TYPE":"Any","END_LINE_NUMBER":27},{"END_CHARACTER":763,"START_LINE_NUMBER":27,"AST_CLASS":"IfExp","LENGTH":4,"START_CHARACTER":743,"VERSION":1,"LABEL":"3","DATA_TYPE":null,"END_LINE_NUMBER":27},{"END_CHARACTER":754,"START_LINE_NUMBER":27,"AST_CLASS":"Compare","LENGTH":7,"START_CHARACTER":747,"VERSION":1,"LABEL":"ò","DATA_TYPE":null,"END_LINE_NUMBER":27},{"END_CHARACTER":701,"START_LINE_NUMBER":25,"AST_CLASS":"Call","LENGTH":10,"START_CHARACTER":691,"VERSION":1,"LABEL":"dim()","DATA_TYPE":"dim()","END_LINE_NUMBER":25},{"END_CHARACTER":672,"START_LINE_NUMBER":23,"AST_CLASS":"Assign","LENGTH":3,"START_CHARACTER":650,"VERSION":1,"LABEL":"½","DATA_TYPE":null,"END_LINE_NUMBER":23},{"END_CHARACTER":750,"START_LINE_NUMBER":27,"AST_CLASS":"Name","LENGTH":3,"START_CHARACTER":747,"VERSION":1,"LABEL":"W","DATA_TYPE":"Any","END_LINE_NUMBER":27}],"COMMITTER_NAME":"tky823","LINK":"https:\/\/github.com\/tky823\/dnn-based_source_separation\/commit\/56dd2a05237a9793a9d2e83550883e8534ee1219#diff-5ff17b3312fc2916b74109703e9ae0ba04940f3f667bfea49b7eed7420b0a3d3L20","COMMIT_NAME":"56dd2a05237a9793a9d2e83550883e8534ee1219","AUTHOR_EMAIL":"delta9guitar97@gmail.com","N FILE_NAME":"egs\/wsj0-mix\/danet\/src\/adhoc_criterion.py","M CLASS_NAME":"SquaredError","N METHOD_NAME":"forward(4)","START_LINE_BEFORE_CODE":23,"M METHOD_NAME":"forward(4)","PARENT_CLASS":"nn.Module","END_LINE_BEFORE_CODE":36,"END_CHARACTER_BEFORE_CODE":981,"TIME":"2021-10-22","AUTHOR_NAME":"tky823","START_CHARACTER_BEFORE_CODE":654,"END_LINE_AFTER_CODE":40,"N CLASS_NAME":"SquaredError","FRAGMENT_ID":17489443,"END_CHARACTER_AFTER_CODE":1101,"START_CHARACTER_AFTER_CODE":646},{"M FILE_NAME":"utils\/detection\/utils.py","PROJECT_NAME":"jintao-huang\/efficientdet_pytorch","COMMITTER_EMAIL":"hjt_study@qq.com","START_LINE_AFTER_CODE":112,"NODE_INFO":[{"END_CHARACTER":3778,"START_LINE_NUMBER":114,"AST_CLASS":"Call","LENGTH":7,"START_CHARACTER":3771,"VERSION":0,"LABEL":"dim()","DATA_TYPE":"dim()","END_LINE_NUMBER":114},{"END_CHARACTER":3745,"START_LINE_NUMBER":112,"AST_CLASS":"If","LENGTH":3,"START_CHARACTER":3645,"VERSION":1,"LABEL":"`","DATA_TYPE":null,"END_LINE_NUMBER":114},{"END_CHARACTER":3737,"START_LINE_NUMBER":113,"AST_CLASS":"Call","LENGTH":11,"START_CHARACTER":3680,"VERSION":1,"LABEL":"function.ValueError()","DATA_TYPE":"function.ValueError()","END_LINE_NUMBER":113},{"END_CHARACTER":3726,"START_LINE_NUMBER":113,"AST_CLASS":"Str","LENGTH":35,"START_CHARACTER":3691,"VERSION":1,"LABEL":"B","DATA_TYPE":"String","END_LINE_NUMBER":113},{"END_CHARACTER":3660,"START_LINE_NUMBER":112,"AST_CLASS":"Compare","LENGTH":12,"START_CHARACTER":3648,"VERSION":1,"LABEL":"ò","DATA_TYPE":null,"END_LINE_NUMBER":112},{"END_CHARACTER":3655,"START_LINE_NUMBER":112,"AST_CLASS":"Call","LENGTH":7,"START_CHARACTER":3648,"VERSION":1,"LABEL":"dim()","DATA_TYPE":"dim()","END_LINE_NUMBER":112},{"END_CHARACTER":3737,"START_LINE_NUMBER":113,"AST_CLASS":"Raise","LENGTH":6,"START_CHARACTER":3674,"VERSION":1,"LABEL":"raise","DATA_TYPE":null,"END_LINE_NUMBER":113},{"END_CHARACTER":3736,"START_LINE_NUMBER":113,"AST_CLASS":"BinOp","LENGTH":3,"START_CHARACTER":3726,"VERSION":1,"LABEL":"á","DATA_TYPE":null,"END_LINE_NUMBER":113},{"END_CHARACTER":0,"START_LINE_NUMBER":0,"AST_CLASS":"Name","LENGTH":0,"START_CHARACTER":0,"VERSION":1,"LABEL":"W","DATA_TYPE":"Any","END_LINE_NUMBER":0},{"END_CHARACTER":3783,"START_LINE_NUMBER":114,"AST_CLASS":"Compare","LENGTH":12,"START_CHARACTER":3771,"VERSION":0,"LABEL":"ò","DATA_TYPE":null,"END_LINE_NUMBER":114},{"END_CHARACTER":3660,"START_LINE_NUMBER":112,"AST_CLASS":"Num","LENGTH":1,"START_CHARACTER":3659,"VERSION":1,"LABEL":"L","DATA_TYPE":"number","END_LINE_NUMBER":112},{"END_CHARACTER":3783,"START_LINE_NUMBER":114,"AST_CLASS":"Num","LENGTH":1,"START_CHARACTER":3782,"VERSION":0,"LABEL":"L","DATA_TYPE":"number","END_LINE_NUMBER":114},{"END_CHARACTER":3730,"START_LINE_NUMBER":113,"AST_CLASS":"Name","LENGTH":1,"START_CHARACTER":3729,"VERSION":1,"LABEL":"W","DATA_TYPE":"Any","END_LINE_NUMBER":113},{"END_CHARACTER":3736,"START_LINE_NUMBER":113,"AST_CLASS":"Call","LENGTH":7,"START_CHARACTER":3729,"VERSION":1,"LABEL":"dim()","DATA_TYPE":"dim()","END_LINE_NUMBER":113},{"END_CHARACTER":3926,"START_LINE_NUMBER":114,"AST_CLASS":"If","LENGTH":3,"START_CHARACTER":3768,"VERSION":0,"LABEL":"`","DATA_TYPE":null,"END_LINE_NUMBER":117}],"COMMITTER_NAME":"Jintao Huang","LINK":"https:\/\/github.com\/jintao-huang\/efficientdet_pytorch\/commit\/1bc8344a81cb3569922e4a181f552806b0b82dc8#diff-ccae16c7aede348d62442851c1aeb977da243c0c9b3ce8aa7c389daa568f8e39L111","COMMIT_NAME":"1bc8344a81cb3569922e4a181f552806b0b82dc8","AUTHOR_EMAIL":"hjt_study@qq.com","N FILE_NAME":"utils\/detection\/utils.py","M CLASS_NAME":"FrozenBatchNorm2d","N METHOD_NAME":"forward(2)","START_LINE_BEFORE_CODE":114,"M METHOD_NAME":"forward(2)","PARENT_CLASS":"nn.Module","END_LINE_BEFORE_CODE":117,"END_CHARACTER_BEFORE_CODE":3926,"TIME":"2020-06-09","AUTHOR_NAME":"Jintao Huang","START_CHARACTER_BEFORE_CODE":3768,"END_LINE_AFTER_CODE":114,"N CLASS_NAME":"FrozenBatchNorm2d","FRAGMENT_ID":17489444,"END_CHARACTER_AFTER_CODE":3745,"START_CHARACTER_AFTER_CODE":3645}],"ID":3401,"PATTERN_SIZE":3}